multichaincli/__init__.py
multichaincli/client.py
multichaincli-1.1.0.dist-info/LICENSE
multichaincli-1.1.0.dist-info/METADATA
multichaincli-1.1.0.dist-info/WHEEL
multichaincli-1.1.0.dist-info/top_level.txt
multichaincli-1.1.0.dist-info/RECORD
