Metadata-Version: 2.1
Name: multichaincli
Version: 1.1.0
Summary: A python binding for Multichain Json-RPC API
Home-page: https://github.com/chainstack/multichaincli
Author: Alex Khaerov, Federico Cardoso
Author-email: alex.khaerov@chainstack.com,federico.cardoso@dxmarkets.com
License: BSD
Keywords: multichain python blockchain jsonrpc
Platform: UNKNOWN
Requires-Dist: requests (>=2.20.0)
